{"name": 109, "children": [{"name": "me encanto!", "size": 2, "children": [{"name": "me encanto!!!", "size": 1, "children": []}, {"name": "me encanto", "size": 1, "children": []}, {"name": "me encanto!!", "size": 1, "children": []}, {"name": "me encanto; todo genial", "size": 1, "children": []}, {"name": "me encanto quedarme en casa helsinki!", "size": 1, "children": []}, {"name": "nuestra primera experiencia en la pagina y me encanto este alojamiento!!", "size": 1, "children": []}, {"name": "me encanto muchisimo!!", "size": 1, "children": []}, {"name": "me  encanto a mi y a mi flia porsupuesto!", "size": 1, "children": []}, {"name": "me encanto la terraza", "size": 1, "children": []}]}, {"name": "nos encanto!", "size": 6, "children": [{"name": "tiene mucho encanto con su inmensa biblioteca; y todo estaba limpio", "size": 1, "children": []}, {"name": "nos encanto la estadia", "size": 1, "children": []}, {"name": "nos encanto super centrico y cero ruido!", "size": 1, "children": []}, {"name": "nos encanto !", "size": 1, "children": []}, {"name": "!nos encanto para volver hacer una nueva escapadita de fin de semana!", "size": 1, "children": []}, {"name": "nos encanto\nrecomindo este alojamiento a todo aquel que quiera conocer esta hermosa ciudad", "size": 1, "children": []}, {"name": "nos encanto y volvimos a reservar unos dias", "size": 1, "children": []}, {"name": "nos encanto", "size": 1, "children": []}, {"name": "florencia es un encanto; nos recibio con mucha amabilidad y predisposicion para ayudarnos en lo que necesitaramos", "size": 1, "children": []}, {"name": "muy lindo tandil nos encanto y seguro volvamos a tandil y a la cabana", "size": 1, "children": []}, {"name": "nos encanto el departamento", "size": 1, "children": []}, {"name": "marisel un encanto", "size": 1, "children": []}, {"name": "simplemente nos encanto y ya tenemos claro que si volvemos a buenos aires volveriamos aqui!", "size": 1, "children": []}, {"name": "villa rio hermoso nos encanto", "size": 1, "children": []}, {"name": "nos encanto buenos aires; es bellisimo; quedamos enamoradas", "size": 1, "children": []}, {"name": "lichi un encanto y predispuesta para cualquier consulta  muchas gracias !!!!", "size": 1, "children": []}, {"name": "un verdadero encanto!", "size": 1, "children": []}, {"name": "nos alojamos en el departamento de marcos y nos encanto", "size": 1, "children": []}, {"name": "y ushuaia nos encanto asi que volveremos para conocerla sin nieve!", "size": 1, "children": []}, {"name": "el estudio de soledad nos encanto!", "size": 1, "children": []}, {"name": "monica es un encanto y nos hizo sentir como en casa", "size": 1, "children": []}, {"name": "nos esperamos ir a dar una vuelta a mar del plata otra veznos encanto!", "size": 1, "children": []}, {"name": "nos encanto y sin duda cuando volvamos a buenos aires escogeriamos quedarnos ahi!", "size": 1, "children": []}, {"name": "nos encanto el departamento; super amplio; limpio; ordenado y comodo para estar", "size": 1, "children": []}, {"name": "nos encanto la casa de lilian!", "size": 1, "children": []}, {"name": "nos encanto la cabana todo genial marina una capa super servicial estuvo muy gentil!", "size": 1, "children": []}, {"name": "nos encanto la estadia en tu casa espero q pronto volvamos a vernos beso grande!!", "size": 1, "children": []}, {"name": "nos encanto todo", "size": 1, "children": []}, {"name": "nos encanto bs", "size": 1, "children": []}, {"name": "estuvimos in buenos aires por dos dias y la ciudad nos encanto!", "size": 1, "children": []}, {"name": "nos encanto; guada super simpatica", "size": 1, "children": []}]}, {"name": "me encanto!!!", "size": 2, "children": [{"name": "me encanto!", "size": 1, "children": []}, {"name": "me encanto", "size": 1, "children": []}, {"name": "me encanto!!", "size": 1, "children": []}, {"name": "me encanto; todo genial", "size": 1, "children": []}, {"name": "me encanto quedarme en casa helsinki!", "size": 1, "children": []}, {"name": "nuestra primera experiencia en la pagina y me encanto este alojamiento!!", "size": 1, "children": []}, {"name": "me encanto muchisimo!!", "size": 1, "children": []}, {"name": "me  encanto a mi y a mi flia porsupuesto!", "size": 1, "children": []}, {"name": "me encanto la terraza", "size": 1, "children": []}]}, {"name": "nos encanto", "size": 3, "children": [{"name": "tiene mucho encanto con su inmensa biblioteca; y todo estaba limpio", "size": 1, "children": []}, {"name": "nos encanto la estadia", "size": 1, "children": []}, {"name": "nos encanto!", "size": 1, "children": []}, {"name": "nos encanto super centrico y cero ruido!", "size": 1, "children": []}, {"name": "nos encanto !", "size": 1, "children": []}, {"name": "!nos encanto para volver hacer una nueva escapadita de fin de semana!", "size": 1, "children": []}, {"name": "nos encanto\nrecomindo este alojamiento a todo aquel que quiera conocer esta hermosa ciudad", "size": 1, "children": []}, {"name": "nos encanto y volvimos a reservar unos dias", "size": 1, "children": []}, {"name": "florencia es un encanto; nos recibio con mucha amabilidad y predisposicion para ayudarnos en lo que necesitaramos", "size": 1, "children": []}, {"name": "muy lindo tandil nos encanto y seguro volvamos a tandil y a la cabana", "size": 1, "children": []}, {"name": "nos encanto el departamento", "size": 1, "children": []}, {"name": "marisel un encanto", "size": 1, "children": []}, {"name": "simplemente nos encanto y ya tenemos claro que si volvemos a buenos aires volveriamos aqui!", "size": 1, "children": []}, {"name": "villa rio hermoso nos encanto", "size": 1, "children": []}, {"name": "nos encanto buenos aires; es bellisimo; quedamos enamoradas", "size": 1, "children": []}, {"name": "lichi un encanto y predispuesta para cualquier consulta  muchas gracias !!!!", "size": 1, "children": []}, {"name": "un verdadero encanto!", "size": 1, "children": []}, {"name": "nos alojamos en el departamento de marcos y nos encanto", "size": 1, "children": []}, {"name": "y ushuaia nos encanto asi que volveremos para conocerla sin nieve!", "size": 1, "children": []}, {"name": "el estudio de soledad nos encanto!", "size": 1, "children": []}, {"name": "monica es un encanto y nos hizo sentir como en casa", "size": 1, "children": []}, {"name": "nos esperamos ir a dar una vuelta a mar del plata otra veznos encanto!", "size": 1, "children": []}, {"name": "nos encanto y sin duda cuando volvamos a buenos aires escogeriamos quedarnos ahi!", "size": 1, "children": []}, {"name": "nos encanto el departamento; super amplio; limpio; ordenado y comodo para estar", "size": 1, "children": []}, {"name": "nos encanto la casa de lilian!", "size": 1, "children": []}, {"name": "nos encanto la cabana todo genial marina una capa super servicial estuvo muy gentil!", "size": 1, "children": []}, {"name": "nos encanto la estadia en tu casa espero q pronto volvamos a vernos beso grande!!", "size": 1, "children": []}, {"name": "nos encanto todo", "size": 1, "children": []}, {"name": "nos encanto bs", "size": 1, "children": []}, {"name": "estuvimos in buenos aires por dos dias y la ciudad nos encanto!", "size": 1, "children": []}, {"name": "nos encanto; guada super simpatica", "size": 1, "children": []}]}]}