{"name": "60", "size": 500, "children": [{"name": "muy bien ubicado", "size": 25, "children": [{"name": "muy bien ubicado!", "size": 2, "children": []}, {"name": "muy comodo y bien ubicado", "size": 2, "children": []}, {"name": "el departamento es muy comodo y esta muy bien ubicado", "size": 2, "children": []}, {"name": "muy recomendado; el departamento es bonito; limpio; bien ubicado", "size": 2, "children": []}, {"name": "bien ubicado cerca de todo", "size": 2, "children": []}, {"name": "el lugar esta muy bien ubicado", "size": 2, "children": []}, {"name": "muy comodo; limpio y bien ubicado", "size": 2, "children": []}, {"name": "el departamento es muy lindo y bien ubicado", "size": 2, "children": []}, {"name": "el apartamento esta muy bien ubicado", "size": 3, "children": []}, {"name": "super bien ubicado", "size": 4, "children": []}, {"name": "departamento muy bien ubicado", "size": 4, "children": []}, {"name": "esta muy bien ubicado", "size": 4, "children": []}, {"name": "el departamento esta muy bien ubicado", "size": 6, "children": []}, {"name": "bien ubicado", "size": 9, "children": []}]}]}